extendable_pydantic_patcher.pth
extendable_pydantic/__init__.py
extendable_pydantic/_patch.py
extendable_pydantic/main.py
extendable_pydantic/models.py
extendable_pydantic/py.typed
extendable_pydantic/utils.py
extendable_pydantic/version.py
extendable_pydantic-1.4.1.dist-info/METADATA
extendable_pydantic-1.4.1.dist-info/WHEEL
extendable_pydantic-1.4.1.dist-info/licenses/LICENSE
extendable_pydantic-1.4.1.dist-info/RECORD
