Metadata-Version: 2.4
Name: extendable_pydantic
Version: 1.4.1
Dynamic: Summary
Project-URL: Source, https://github.com/lmignon/extendable-pydantic
Author-email: Laurent Mignon <laurent.mignon@acsone.eu>
License: MIT License
License-File: LICENSE
Classifier: Intended Audience :: Developers
Classifier: License :: OSI Approved :: MIT License
Classifier: Operating System :: OS Independent
Requires-Python: >=3.7
Requires-Dist: extendable>=1.3.0
Requires-Dist: pydantic>=2.0.2
Requires-Dist: wrapt
Provides-Extra: mypy
Requires-Dist: mypy>=1.4.1; extra == 'mypy'
Provides-Extra: release
Requires-Dist: bumpversion; extra == 'release'
Requires-Dist: towncrier; extra == 'release'
Provides-Extra: test
Requires-Dist: coverage[toml]; extra == 'test'
Requires-Dist: fastapi>=0.111; extra == 'test'
Requires-Dist: httpx; extra == 'test'
Requires-Dist: pytest; extra == 'test'
